drift/__init__.py
drift/config.py
drift/exceptions.py
drift/monitor.py
drift_sre-0.1.0.dist-info/licenses/LICENSE
drift_sre-0.1.0.dist-info/METADATA
drift_sre-0.1.0.dist-info/WHEEL
drift_sre-0.1.0.dist-info/top_level.txt
drift_sre-0.1.0.dist-info/RECORD
