Metadata-Version: 2.4
Name: drift-sre
Version: 0.1.0
Summary: Real-time Anomaly Detection Library for SRE with Discord notifications
Home-page: https://github.com/soumilsuri/Drift
Author: soumilsuri
License: MIT
Project-URL: Documentation, https://github.com/soumilsuri/Drift#readme
Project-URL: Source, https://github.com/soumilsuri/Drift
Project-URL: Tracker, https://github.com/soumilsuri/Drift/issues
Keywords: monitoring,anomaly-detection,sre,discord,alerts,metrics
Classifier: Development Status :: 4 - Beta
Classifier: Intended Audience :: Developers
Classifier: Intended Audience :: System Administrators
Classifier: Topic :: System :: Monitoring
Classifier: License :: OSI Approved :: MIT License
Classifier: Programming Language :: Python :: 3
Classifier: Programming Language :: Python :: 3.8
Classifier: Programming Language :: Python :: 3.9
Classifier: Programming Language :: Python :: 3.10
Classifier: Programming Language :: Python :: 3.11
Classifier: Programming Language :: Python :: 3.12
Requires-Python: >=3.8
License-File: LICENSE
Requires-Dist: psutil>=5.9.0
Requires-Dist: requests>=2.28.0
Provides-Extra: dev
Requires-Dist: pytest>=7.0.0; extra == "dev"
Requires-Dist: pytest-cov>=4.0.0; extra == "dev"
Dynamic: home-page
Dynamic: license-file
Dynamic: requires-python
